["```go\nFROM scratch \nMAINTAINER Your Name <your@email.address> \nADD vaultd vaultd \nEXPOSE 8080 8081 \nENTRYPOINT [\"/vaultd\"] \n\n```", "```go\nCGO_ENABLED=0 GOOS=linux go build -a ./cmd/vaultd/\n\n```", "```go\ndocker build -t vaultd\n\n```", "```go\nStep 1 : FROM scratch\n --->\nStep 2 : MAINTAINER Your Name <your@email.address>\n ---> Using cache\n ---> a8667f8f0881\nStep 3 : ADD vaultd vaultd\n ---> 0561c999c1e3\nRemoving intermediate container 4b75fde507df\nStep 4 : EXPOSE 8080 8081\n ---> Running in 8f169f5b3b44\n ---> 1d7758c20b3a\nRemoving intermediate container 8f169f5b3b44\nStep 5 : ENTRYPOINT /vaultd\n ---> Running in b5d55d6429be\n ---> b7178985dddf\nRemoving intermediate container b5d55d6429be\nSuccessfully built b7178985dddf\n\n```", "```go\ndocker run -p 6060:8080 -p 6061:8081 --name localtest --rm vaultd\n\n```", "```go\n2016/09/20 15:56:17 grpc: :8081\n2016/09/20 15:56:17 http: :8080\n\n```", "```go\ncurl -XPOST -d '{\"password\":\"monkey\"}' localhost:6060/hash\n\n```", "```go\n{\"hash\":\"$2a$0$wk4qc74ougOkbkt/TWuRQHSg03i1ataNupbDADBwpe\"}\n\n```", "```go\ndocker ps\n\n```", "```go\ndocker stop localtest\n\n```", "```go\ndocker login -u **USERNAME** -p **PASSWORD** https://index.docker.io/v1/\n\n```", "```go\ndocker build -t USERNAME/vault\n\n```", "```go\ndocker push USERNAME/vault\n\n```", "```go\nf477b97e9e48: Pushed\n384c907d1173: Pushed\n80168d020f50: Pushed\n0ceba54dae47: Pushed\n4d7388e75674: Pushed\nf042db76c15c: Pushing [====>               ] 21.08 MB/243.6 MB\nd15a527c2ee1: Pushing [=====>              ] 15.77 MB/134 MB\n751f5d9ad6db: Pushing [======>             ] 16.49 MB/122.6 MB\n17587239b3df: Pushing [===================>] 17.01 MB/44.31 MB\n9e63c5bce458: Pushing [==================> ] 65.58 MB/125.1 MB\n\n```", "```go\ndocker pull USERNAME/vault\n\n```", "```go\ndocker run -d -p 6060:8080 -p 6061:8081 --name vault USERNAME/vault\n\n```", "```go\ncurl -XPOST -d '{\"password\":\"Monkey\"}' http://IPADDRESS:6060/hash\n\n```", "```go\n{\"hash\":\"$2a$10$eGFGRZ2zMfsXss.6CgK6/N7TsmF.6MAv6i7Km4AHC\"}\n\n```", "```go\necho $PATH\n\n```", "```go\n/usr/local/bin:/usr/bin:/bin:/opt/go/bin\n\n```", "```go\ngo version\n\n```", "```go\ngo version go1.77.1 darwin/amd64\n\n```", "```go\ngo get github.com/matryer/silk\n\n```", "```go\npackage main \nimport ( \n  \"fmt\" \n) \nfunc main() { \n  return \n  var name string \n  name = \"Mat\" \n  fmt.Println(\"Hello \", name) \n} \n\n```", "```go\ngo fmt -w\n\n```", "```go\npackage main  \nimport ( \n  \"fmt\" \n)  \nfunc main() { \n  return \n  var name string \n  name = \"Mat\" \n  fmt.Println(\"Hello \", name) \n} \n\n```", "```go\ngo vet\n\n```", "```go\nmain.go:10: unreachable code\nexit status 1\n\n```", "```go\ngo get golang.org/x/tools/cmd/goimports\n\n```", "```go\nimport ( \n  \"net/http\" \n  \"sync\" \n) \n\n```", "```go\n./main.go:4: imported and not used: \"net/http\"\n./main.go:5: imported and not used: \"sync\"\n./main.go:13: undefined: fmt\n\n```", "```go\ngoimports -w *.go\n\n```", "```go\n\"on_save\": [ \n  { \n    \"cmd\": \"gs9o_open\",  \n    \"args\": { \n      \"run\": [\"sh\", \"go build . errors && go test -i && go test && \n       go vet && golint\"], \n      \"focus_view\": false \n    } \n  } \n] \n\n```", "```go\nmain.go:8: unreachable code\n\n```", "```go\n\"fmt_cmd\": [\"goimports\"]\n\n```"]